{"openapi":"3.0.1","info":{"title":"Moneygment API","description":"The list of api for Moneygment App","version":"1.0","contact":{"name":"Nessotech Inc.","email":"it-tech@nessotech.com"}},"servers":[{"url":"http://172.16.1.48:8080","description":"Development server"},{"url":"https://system.moneygment.ph","description":"Production server"}],"security":[{"bearerAuth":[]}],"paths":{"/webapi/user":{"get":{"parameters":[{"name":"uid","in":"header","description":"firebase uid","schema":{"type":"string"},"required":true,"example":null}],"responses":{"200":{"description":"OK","content":{"application/json":{"schema":{"$ref":"#/components/schemas/UserAccount"}}}},"204":{"description":"No Data - need to create a user account"}},"tags":["User account"]},"post":{"requestBody":{"description":"","required":true,"content":{"application/json":{"schema":{"$ref":"#/components/schemas/UserAccount"}}}},"responses":{"200":{"description":"OK","content":{"application/json":{"schema":{"$ref":"#/components/schemas/UserAccount"}}}}},"tags":["User account"]},"put":{"requestBody":{"description":"","required":true,"content":{"application/json":{"schema":{"$ref":"#/components/schemas/UserAccount"}}}},"responses":{"200":{"description":"OK","content":{"application/json":{"schema":{"$ref":"#/components/schemas/UserAccount"}}}}},"tags":["User account"]}},"/webapi/personal":{"get":{"parameters":[{"name":"uid","in":"header","description":"user account uid","schema":{"type":"string"},"required":true,"example":null}],"responses":{"200":{"description":"OK","content":{"application/json":{"schema":{"type":"array","items":{"$ref":"#/components/schemas/PersonalAccount"}}}}}},"tags":["Personal Account"]},"post":{"parameters":[{"name":"user","in":"header","description":"user account uid","schema":{"type":"string"},"required":true,"example":null}],"requestBody":{"description":"","required":true,"content":{"application/json":{"schema":{"$ref":"#/components/schemas/PersonalAccount"}}}},"responses":{"200":{"description":"OK","content":{"application/json":{"schema":{"$ref":"#/components/schemas/PersonalAccount"}}}}},"tags":["Personal Account"]},"put":{"parameters":[{"name":"id","in":"header","description":"personal account ID","schema":{"type":"string"},"required":true,"example":null},{"name":"uid","in":"header","description":"user account uid","schema":{"type":"string"},"required":true,"example":null}],"requestBody":{"description":"","required":true,"content":{"application/json":{"schema":{"$ref":"#/components/schemas/PersonalAccount"}}}},"responses":{"200":{"description":"OK","content":{"application/json":{"schema":{"$ref":"#/components/schemas/PersonalAccount"}}}}},"tags":["Personal Account"]}},"/webapi/government":{"get":{"parameters":[{"name":"uid","in":"header","description":"user account uid","schema":{"type":"string"},"required":true,"example":null}],"responses":{"200":{"description":"OK","content":{"application/json":{"schema":{"type":"array","items":{"$ref":"#/components/schemas/GovernmentAccount"}}}}}},"tags":["Government Account"]}},"/webapi/government/account":{"post":{"parameters":[{"name":"personalID","in":"header","description":"personal account ID","schema":{"type":"string"},"required":true,"example":null}],"requestBody":{"description":"","required":true,"content":{"application/json":{"schema":{"$ref":"#/components/schemas/GovernmentAccount"}}}},"responses":{"200":{"description":"OK","content":{"application/json":{"schema":{"$ref":"#/components/schemas/GovernmentAccount"}}}}},"tags":["Government Account"]},"put":{"parameters":[{"name":"id","in":"header","description":"government account ID","schema":{"type":"string"},"required":true,"example":null},{"name":"personID","in":"header","description":"personal account ID","schema":{"type":"string"},"required":true,"example":null}],"requestBody":{"description":"","required":true,"content":{"application/json":{"schema":{"$ref":"#/components/schemas/GovernmentAccount"}}}},"responses":{"200":{"description":"OK","content":{"application/json":{"schema":{"$ref":"#/components/schemas/GovernmentAccount"}}}}},"tags":["Government Account"]}},"/webapi/personal/main":{"get":{"parameters":[{"name":"uid","in":"header","description":"firebase uid","schema":{"type":"string"},"required":true,"example":null}],"responses":{"200":{"description":"OK","content":{"application/json":{"schema":{"$ref":"#/components/schemas/PersonalAccount"}}}}},"tags":["Main Profile"]}},"/webapi/personal/active":{"get":{"parameters":[{"name":"uid","in":"header","description":"firebase uid","schema":{"type":"string"},"required":true,"example":null}],"responses":{"200":{"description":"OK","content":{"application/json":{"schema":{"type":"array","items":{"$ref":"#/components/schemas/PersonalAccount"}}}}}},"tags":["Beneficiary"]}},"/webapi/personal/inactive":{"get":{"parameters":[{"name":"uid","in":"header","description":"firebase uid","schema":{"type":"string"},"required":true,"example":null}],"responses":{"200":{"description":"OK","content":{"application/json":{"schema":{"type":"array","items":{"$ref":"#/components/schemas/PersonalAccount"}}}}}},"tags":["Beneficiary"]}},"/webapi/personal/activate":{"get":{"parameters":[{"name":"pid","in":"header","description":"personal account ID","schema":{"type":"string"},"required":true,"example":null}],"responses":{"200":{"description":"OK","content":{"application/json":{"schema":{"type":"array","items":{"$ref":"#/components/schemas/PersonalAccount"}}}}}},"tags":["Beneficiary Action"]}},"/webapi/personal/deactivate":{"get":{"parameters":[{"name":"pid","in":"header","description":"personal account ID","schema":{"type":"string"},"required":true,"example":null}],"responses":{"200":{"description":"OK","content":{"application/json":{"schema":{"type":"array","items":{"$ref":"#/components/schemas/PersonalAccount"}}}}}},"tags":["Beneficiary Action"]}},"/webapi/support/module/config":{"get":{"parameters":[{"name":"module","in":"header","description":"module name","schema":{"type":"string"},"required":true,"example":null},{"name":"sub","in":"header","description":"sub module name","schema":{"type":"string"},"required":true}],"responses":{"200":{"description":"OK","content":{"application/json":{"schema":{"$ref":"#/components/schemas/ModuleConfiguration"}}}}},"tags":["Module Configuration"]}},"/webapi/wallet":{"get":{"parameters":[{"name":"userId","in":"header","description":"user account id","schema":{"type":"string"},"required":true,"example":null},{"name":"currency","in":"header","description":"currency of user wallet","schema":{"type":"string"},"required":true,"example":"PHP"}],"responses":{"200":{"description":"OK","content":{"application/json":{"schema":{"$ref":"#/components/schemas/Wallet"}}}}},"tags":["Wallet"]}},"/webapi/wallet/history":{"get":{"parameters":[{"name":"userWallet","in":"header","description":"user wallet id","schema":{"type":"string"},"required":true,"example":null}],"responses":{"200":{"description":"OK","content":{"application/json":{"schema":{"$ref":"#/components/schemas/WalletHistory"}}}}},"tags":["Wallet Transactions"]}},"/webapi/wallet/transactions":{"get":{"parameters":[{"name":"walletID","in":"header","description":"user wallet id","schema":{"type":"string"},"required":true,"example":null}],"responses":{"200":{"description":"OK","content":{"application/json":{"schema":{"type":"array","items":{"$ref":"#/components/schemas/WalletTransaction"}}}}}},"tags":["Wallet Transactions"]}},"/webapi/wallet/limit":{"get":{"parameters":[{"name":"walletID","in":"header","description":"user wallet id","schema":{"type":"string"},"required":true,"example":null}],"responses":{"200":{"description":"OK","content":{"application/json":{"schema":{"type":"string"}}}}},"tags":["Wallet Limit"]}},"/webapi/wallet/topup":{"post":{"parameters":[{"name":"userWallet","in":"header","description":"user wallet id","schema":{"type":"string"},"required":true,"example":null},{"name":"flow","in":"header","description":"cashflow of the wallet","schema":{"type":"string"},"required":true,"example":"fundReplenishment"},{"name":"modeOfPayment","in":"header","description":"mode of payment","schema":{"type":"string","enum":["CTA","ECPAY","PAYPAL","DRAGON","7-11"]},"required":true,"example":null},{"name":"amount","in":"header","description":"amount of the transaction","schema":{"type":"string"},"required":true,"example":null},{"name":"serviceCharge","in":"header","description":"service fee","schema":{"type":"string"},"required":true,"example":null},{"name":"partnerFee","in":"header","description":"mode of payment partner fee","schema":{"type":"string"},"required":true,"example":null}],"responses":{"200":{"description":"OK","content":{"application/json":{"schema":{"$ref":"#/components/schemas/Wallet"}}}}},"tags":["Wallet Topup"]}},"/webapi/sms/otp":{"post":{"parameters":[{"name":"deviceType","in":"query","description":"query parameter ios or android type of device","schema":{"type":"string"},"required":true,"example":"android"},{"name":"accountId","in":"query","description":"query parameter this is the main personalAccountId","schema":{"type":"string"},"required":true,"example":null}],"responses":{"200":{"description":"OK","content":{"application/json":{"schema":{"$ref":"#/components/schemas/GenericResponse"}}}}},"tags":["OTP"]}},"/webapi/sms/email/otp":{"post":{"parameters":[{"name":"deviceType","in":"query","description":"query parameter ios or android type of device","schema":{"type":"string"},"required":true,"example":"android"},{"name":"accountId","in":"query","description":"query parameter this is the main personalAccountId","schema":{"type":"string"},"required":true,"example":null}],"responses":{"200":{"description":"OK","content":{"application/json":{"schema":{"$ref":"#/components/schemas/GenericResponse"}}}}},"tags":["OTP"]}},"/webapi/sms/otp/validate":{"put":{"parameters":[{"name":"code","in":"query","description":"query parameter this is the 6 digit code for OTP","schema":{"type":"string"},"required":true,"example":null},{"name":"accountId","in":"query","description":"query parameter this is the main personalAccountId","schema":{"type":"string"},"required":true,"example":null}],"responses":{"200":{"description":"OK","content":{"application/json":{"schema":{"$ref":"#/components/schemas/GenericResponse"}}}}},"tags":["OTP"]}},"/webapi/wallet/account":{"get":{"parameters":[{"name":"accountNo","in":"header","description":"user wallet account number","schema":{"type":"string"},"required":true,"example":null}],"responses":{"200":{"description":"OK"}},"tags":["Wallet to Wallet"]}},"/webapi/wallet/transfer":{"post":{"parameters":[{"name":"source","in":"header","description":"user wallet id of the sender","schema":{"type":"string"},"required":true,"example":null},{"name":"destination","in":"header","description":"user wallet id of the beneficiary","schema":{"type":"string"},"required":true,"example":null},{"name":"amount","in":"header","description":"transfer amount of the transaction","schema":{"type":"number"},"required":true,"example":null},{"name":"remarks","in":"header","description":"reason for transfer","schema":{"type":"string"},"required":false,"example":"This is a sample remarks"}],"responses":{"200":{"description":"OK"}},"tags":["Wallet to Wallet"]}},"/webapi/wallet/cashout/route":{"get":{"responses":{"200":{"description":"OK","content":{"application/json":{"schema":{"$ref":"#/components/schemas/CashoutRoute"}}}}},"tags":["Cashout"]}},"/webapi/wallet/cashout":{"post":{"parameters":[{"name":"walletID","in":"header","description":"user wallet id of the sender","schema":{"type":"string"},"required":true,"example":null}],"requestBody":{"description":"","required":true,"content":{"application/json":{"schema":{"$ref":"#/components/schemas/CashoutRequest"}}}},"responses":{"200":{"description":"OK","content":{"application/json":{"schema":{"$ref":"#/components/schemas/CashoutResponse"}}}}},"tags":["Cashout"]}},"/webapi/level/userlevel/{useraccountId}":{"get":{"parameters":[{"name":"useraccountId","in":"path","description":"user account id of the current user","schema":{"type":"string"},"required":true,"example":null}],"responses":{"200":{"description":"OK","content":{"application/json":{"schema":{"$ref":"#/components/schemas/UserLevel"}}}}},"tags":["Limits and Verification"]}},"/webapi/level/requestlevel":{"put":{"parameters":[{"name":"useraccountId","in":"query","description":"user account id of the current user","schema":{"type":"string"},"required":true,"example":null},{"name":"level","in":"query","description":"level to be requested","schema":{"type":"string"},"required":true,"example":null},{"name":"action","in":"query","description":"action of the particular level requested","schema":{"type":"string","enum":["EMV (Email Verification)","IDV (ID Verification)","SIDV (Selfie w/ ID Verification)","CAV (Callback Verification)"]},"required":true,"example":null}],"responses":{"200":{"description":"OK","content":{"application/json":{"schema":{"$ref":"#/components/schemas/GenericResponse"}}}}},"tags":["Limits and Verification"]}},"/webapi/level/requestlevel/upload":{"put":{"parameters":[{"name":"useraccountId","in":"query","description":"user account id of the current user","schema":{"type":"string"},"required":true,"example":null},{"name":"level","in":"query","description":"user account id of the current user","schema":{"type":"string"},"required":true,"example":null},{"name":"action","in":"query","description":"user account id of the current user","schema":{"type":"string","enum":["EMV","IDV","SIDV","CAV"]},"required":true,"example":null},{"name":"idType","in":"query","description":"id type","schema":{"type":"string","enum":["Passport ID","Voter's ID","Postal ID","BIR ID","TIN ID","PhilHealth ID","Driver’s License","Residence ID","Unified Multi-Purpose ID (UMID)","Professional Regulation Commission (PRC) ID","Seaman’s Book (Seafarer’s Identification & Record Book)"]},"required":true,"example":null},{"name":"idNo","in":"query","description":"id number of uploaded image","schema":{"type":"string"},"required":false,"example":null},{"name":"uploadedFile","in":"path","description":"The image file to upload.","schema":{"type":"string","format":"binary"},"required":true}],"responses":{"200":{"description":"OK","content":{"application/json":{"schema":{"$ref":"#/components/schemas/GenericResponse"}}}}},"tags":["Limits and Verification"]}},"/webapi/packages":{"get":{"parameters":[{"name":"id","in":"header","description":"package id","schema":{"type":"string"},"required":true,"example":null}],"responses":{"200":{"description":"OK","content":{"application/json":{"schema":{"$ref":"#/components/schemas/Packages"}}}}},"tags":["Packages"]}},"/webapi/packages/all":{"get":{"responses":{"200":{"description":"OK","content":{"application/json":{"schema":{"type":"array","items":{"$ref":"#/components/schemas/Packages"}}}}}},"tags":["Packages"]}},"/webapi/packages/name":{"get":{"parameters":[{"name":"name","in":"header","description":"package name","schema":{"type":"string","enum":["One-time Availment SSS","One-time Availment SSS Employer","One-time Availment SSS Employer Big","One-time Availment SSS OFW","One-time Availment PhilHealth","One-time Availment PhilHealth OFW","One-time Availment PhilHealth Employer","One-time Availment PhilHealth Employer Big","One-time Availment Pagibig","One-time Availment Pagibig OFW","One-time Availment Pagibig Employer","One-time Availment Pagibig Employer Big"]},"required":true,"example":null}],"responses":{"200":{"description":"OK","content":{"application/json":{"schema":{"type":"string"}}}}},"tags":["Packages"]}},"/webapi/packages/services":{"get":{"parameters":[{"name":"packageId","in":"header","description":"package ID","schema":{"type":"string"},"required":true,"example":null}],"responses":{"200":{"description":"OK","content":{"application/json":{"schema":{"type":"array","items":{"$ref":"#/components/schemas/Services"}}}}}},"tags":["Packages"]}},"/webapi/partner/fees":{"get":{"responses":{"200":{"description":"OK","content":{"application/json":{"schema":{"type":"array","items":{"$ref":"#/components/schemas/PartnerFees"}}}}}},"tags":["Partner Fees"]}},"/webapi/pagibig/validate":{"post":{"parameters":[{"name":"pagibigNumber","in":"header","description":"Pag-IBIG number","schema":{"type":"string"},"required":true,"example":null}],"responses":{"200":{"description":"OK","content":{"application/json":{"schema":{"$ref":"#/components/schemas/PagIBIGResponse"}}}}},"tags":["Pag-IBIG"]}},"/webapi/pagibig/employer/validate":{"get":{"parameters":[{"name":"pin","in":"header","description":"employer PIN","schema":{"type":"string"},"required":true,"example":null}],"responses":{"200":{"description":"OK","content":{"application/json":{"schema":{"$ref":"#/components/schemas/PagIBIGEmployerInfo"}}}}},"tags":["Pag-IBIG"]}},"/webapi/pagibig":{"get":{"parameters":[{"name":"uid","in":"header","description":"user account uid","schema":{"type":"string"},"required":true,"example":null}],"responses":{"200":{"description":"OK","content":{"application/json":{"schema":{"type":"array","items":{"$ref":"#/components/schemas/PagIBIGResponse"}}}}}},"tags":["Pag-IBIG"]},"post":{"parameters":[{"name":"govtServerID","in":"header","description":"government account ID","schema":{"type":"string"},"required":true,"example":null},{"name":"packageID","in":"header","description":"packageID","schema":{"type":"string"},"required":true,"example":null}],"requestBody":{"description":"","required":true,"content":{"application/json":{"schema":{"$ref":"#/components/schemas/PagIBIGRequest"}}}},"responses":{"200":{"description":"OK","content":{"application/json":{"schema":{"$ref":"#/components/schemas/PagIBIGResponse"}}}}},"tags":["Pag-IBIG"]}},"/webapi/philhealth":{"get":{"parameters":[{"name":"uid","in":"header","description":"user account uid","schema":{"type":"string"},"required":true,"example":null}],"responses":{"200":{"description":"OK","content":{"application/json":{"schema":{"type":"array","items":{"$ref":"#/components/schemas/PhilHealthResponse"}}}}}},"tags":["PhilHealth"]},"post":{"parameters":[{"name":"govtServerID","in":"header","description":"government account ID","schema":{"type":"string"},"required":true,"example":null},{"name":"packageID","in":"header","description":"packageID","schema":{"type":"string"},"required":true,"example":null}],"requestBody":{"description":"","required":true,"content":{"application/json":{"schema":{"$ref":"#/components/schemas/PhilHealthRequest"}}}},"responses":{"200":{"description":"OK","content":{"application/json":{"schema":{"$ref":"#/components/schemas/PhilHealthResponse"}}}}},"tags":["PhilHealth"]}},"/webapi/sss/prn/requestSSSPRN":{"post":{"parameters":[{"name":"membershipType","in":"header","description":"membership type","schema":{"type":"string","enum":["s"]},"required":true,"example":null},{"name":"sssNum","in":"header","description":"sss number","schema":{"type":"string"},"required":true,"example":null},{"name":"amount","in":"header","description":"amount","schema":{"type":"string"},"required":true,"example":null},{"name":"startDate","in":"header","description":"start date","schema":{"type":"string"},"required":true,"example":null},{"name":"endDate","in":"header","description":"end date","schema":{"type":"string"},"required":true,"example":null},{"name":"govtAccountId","in":"header","description":"government account id","schema":{"type":"string"},"required":true,"example":null}],"responses":{"200":{"description":"OK","content":{"application/json":{"schema":{"type":"array","items":{"$ref":"#/components/schemas/MemberBean"}}}}}},"tags":["SSS PRN"]}},"/webapi/sss/prn/inquireStatusSSSPRN":{"get":{"parameters":[{"name":"prn","in":"header","description":"sss prn","schema":{"type":"string"},"required":true,"example":null}],"responses":{"200":{"description":"OK","content":{"application/json":{"schema":{"$ref":"#/components/schemas/MemberBean"}}}}},"tags":["SSS PRN"]}},"/webapi/sss/prn/inquireEmployerSSSPRN":{"get":{"parameters":[{"name":"prn","in":"header","description":"sss employer prn","schema":{"type":"string"},"required":true,"example":null}],"responses":{"200":{"description":"OK","content":{"application/json":{"schema":{"$ref":"#/components/schemas/EmployerBean"}}}}},"tags":["SSS PRN"]}},"/webapi/sss/contribution":{"get":{"parameters":[{"name":"uid","in":"header","description":"user account uid","schema":{"type":"string"},"required":true,"example":null}],"responses":{"200":{"description":"OK","content":{"application/json":{"schema":{"type":"array","items":{"$ref":"#/components/schemas/SSSResponse"}}}}}},"tags":["SSS Contribution"]},"post":{"parameters":[{"name":"govtServerID","in":"header","description":"government account ID","schema":{"type":"string"},"required":true,"example":null},{"name":"packageID","in":"header","description":"packageID","schema":{"type":"string"},"required":true,"example":null}],"requestBody":{"description":"","required":true,"content":{"application/json":{"schema":{"$ref":"#/components/schemas/SSSContributionRequest"}}}},"responses":{"200":{"description":"OK","content":{"application/json":{"schema":{"$ref":"#/components/schemas/SSSResponse"}}}}},"tags":["SSS Contribution"]}},"/webapi/sss/salaryloan":{"get":{"parameters":[{"name":"uid","in":"header","description":"user account uid","schema":{"type":"string"},"required":true,"example":null}],"responses":{"200":{"description":"OK","content":{"application/json":{"schema":{"type":"array","items":{"$ref":"#/components/schemas/SSSResponse"}}}}}},"tags":["SSS Salary Loan"]},"post":{"parameters":[{"name":"govtServerID","in":"header","description":"government account ID","schema":{"type":"string"},"required":true,"example":null},{"name":"packageID","in":"header","description":"packageID","schema":{"type":"string"},"required":true,"example":null}],"requestBody":{"description":"","required":true,"content":{"application/json":{"schema":{"$ref":"#/components/schemas/SSSSalaryLoanRequest"}}}},"responses":{"200":{"description":"OK","content":{"application/json":{"schema":{"$ref":"#/components/schemas/SSSResponse"}}}}},"tags":["SSS Salary Loan"]}},"/webapi/sss/realestate":{"get":{"parameters":[{"name":"uid","in":"header","description":"user account uid","schema":{"type":"string"},"required":true,"example":null}],"responses":{"200":{"description":"OK","content":{"application/json":{"schema":{"type":"array","items":{"$ref":"#/components/schemas/SSSResponse"}}}}}},"tags":["SSS Real Estate"]},"post":{"parameters":[{"name":"govtServerID","in":"header","description":"government account ID","schema":{"type":"string"},"required":true,"example":null},{"name":"packageID","in":"header","description":"packageID","schema":{"type":"string"},"required":true,"example":null}],"requestBody":{"description":"","required":true,"content":{"application/json":{"schema":{"$ref":"#/components/schemas/SSSRealEstateRequest"}}}},"responses":{"200":{"description":"OK","content":{"application/json":{"schema":{"$ref":"#/components/schemas/SSSResponse"}}}}},"tags":["SSS Real Estate"]}},"/webapi/notification/notifications":{"get":{"responses":{"200":{"description":"OK","content":{"application/json":{"schema":{"type":"array","items":{"$ref":"#/components/schemas/Notification"}}}}}},"tags":["Notification"]}},"/webapi/verifyaccesstoken":{"get":{"parameters":[{"name":"accessToken","in":"header","description":"access token of the user","schema":{"type":"string"},"required":true,"example":null}],"responses":{"200":{"description":"OK","content":{"application/json":{"schema":{"$ref":"#/components/schemas/AccessTokenJwt"}}}}},"tags":["Tokens"]}},"/webapi/auth/refreshToken":{"get":{"parameters":[{"name":"refreshToken","in":"header","description":"refresh token of the user","schema":{"type":"string"},"required":true,"example":null}],"responses":{"200":{"description":"OK","content":{"application/json":{"schema":{"$ref":"#/components/schemas/AccessTokenJwt"}}}}},"tags":["Tokens"]}}},"components":{"securitySchemes":{"bearerAuth":{"type":"http","scheme":"bearer","bearerFormat":"JWT"}},"schemas":{"GenericResponse":{"type":"object","properties":{"message":{"type":"string","description":"message of request","example":"test message"},"result":{"type":"string","description":"result of request Ok, Fail or Expired, added Invalid for invalid number format.","example":"Ok"},"id":{"type":"string","description":"id you can ignore this.","example":null}}},"CashoutRoute":{"type":"object","properties":{"id":{"type":"string","description":"cashout route id","example":null},"created":{"type":"string","description":"cashout route date created","example":null},"version":{"type":"string","description":"cashout route date modified"},"deleted":{"type":"string","description":"cashout route date deleted","example":null},"route":{"type":"string","description":"cashout route","enum":["EEC","Cavalli"],"example":null},"type":{"type":"string","description":"cashout route type","enum":["CTA (Bank)","PU (Pickup)"],"example":null},"details":{"type":"string","description":"merchants name","example":null},"fee":{"type":"number","description":"amount fee of the particular merchant","example":null}}},"CashoutRequest":{"type":"object","properties":{"amount":{"type":"number","description":"cashout amount","example":null},"fee":{"type":"number","description":"merchant amount fee","example":null},"transactionType":{"type":"string","description":"cashout route type","example":null},"details1":{"type":"string","description":"merchant name","example":null},"details2":{"type":"string","description":"account number on a particular merchant","example":null},"route":{"type":"string","description":"cashout route","example":null}}},"CashoutResponse":{"type":"object","properties":{"id":{"type":"string","description":"cashout id","example":null},"created":{"type":"string","description":"cashout date created","example":null},"version":{"type":"string","description":"cashout date modified"},"deleted":{"type":"string","description":"cashout date deleted","example":null},"amount":{"type":"number","description":"cashout amount","example":null},"fee":{"type":"number","description":"merchant amount fee","example":null},"cashflow":{"type":"object","description":"","example":null},"transactionType":{"type":"string","description":"cashout route type","example":null},"details1":{"type":"string","description":"merchant name","example":null},"details2":{"type":"string","description":"account number on a particular merchant","example":null},"responseCode":{"type":"string","description":"","example":null},"responseDesc":{"type":"string","description":"","example":null},"route":{"type":"string","description":"cashout route","example":null},"batch":{"type":"string","description":"","example":null},"status":{"type":"string","description":"","example":null,"enum":["failed","paid","awaiting payment"]},"errorMessage":{"type":"string","description":"","example":null}}},"ModuleConfiguration":{"type":"object","properties":{"id":{"type":"number","description":"id","example":null},"created":{"type":"string","description":"module configuration date created","example":null},"version":{"type":"string","description":"module configuration date modified","example":null},"deleted":{"type":"string","description":"module configuration date deleted","example":null},"module":{"type":"string","description":"module configuration name","example":null},"sub":{"type":"string","description":"module configuration sub module name","example":null},"enable":{"type":"string","description":"module configuration status","example":null}}},"Wallet":{"type":"object","properties":{"id":{"type":"string","description":"wallet id","example":null},"created":{"type":"string","description":"wallet date created","example":null},"version":{"type":"string","description":"wallet date modified"},"deleted":{"type":"string","description":"wallet date deleted","example":null},"currency":{"type":"number","description":"wallet currency","example":null},"userAccount":{"$ref":"#/components/schemas/UserAccount"},"currentPoint":{"type":"number","description":"current reward points","example":null},"currentBalance":{"type":"number","description":"wallet current balance","example":null},"accountNo":{"type":"string","description":"wallet account number","example":null},"token":{"type":"string","description":"token","example":null},"url":{"type":"string","description":"url of the payment method","example":null},"errorMessage":{"type":"string","description":"error message of the transaction","example":null},"referenceNo":{"type":"string","description":"reference number of the transaction","example":null}}},"WalletHistory":{"type":"object","properties":{"date":{"type":"string","description":"date of transactions","example":null},"entryList":{"type":"array","items":{"$ref":"#/components/schemas/EntryList"}}}},"EntryList":{"type":"object","properties":{"referenceNo":{"type":"string","description":"reference number of the transaction","example":null},"status":{"type":"string","description":"transaction status","example":null},"modeOfPayment":{"type":"string","description":"mode of payment of the transaction","example":null},"createdDay":{"type":"string","description":"created day of the transaction","example":null},"createdTimestamp":{"type":"string","description":"date of transaction","example":null},"description":{"type":"string","description":"transaction description","example":null},"amount":{"type":"string","description":"amount of the transaction","example":null}}},"WalletTransaction":{"type":"object","properties":{"id":{"type":"string","description":"transaction server id","example":null},"transactionId":{"type":"string","description":"transaction id","example":null},"timeStamp":{"type":"string","description":"transaction timestamp","example":null},"description":{"type":"string","description":"transaction description","example":null},"status":{"type":"string","description":"transaction status","example":null},"amount":{"type":"number","description":"transaction amount","example":null}}},"UserAccount":{"type":"object","properties":{"id":{"type":"string","description":"user account id","example":null},"created":{"type":"string","description":"user account date created","example":null},"version":{"type":"string","description":"user account date modified"},"deleted":{"type":"string","description":"user account dsate deleted","example":null},"uid":{"type":"number","description":"firebase uid","example":null},"email":{"type":"string","description":"user account email address","example":null},"subscribed":{"type":"boolean","description":"","example":null},"tutorial":{"type":"number","description":"","example":null},"device":{"type":"string","description":"user device type (android or ios)","example":null},"referralCode":{"type":"string","description":"user referral code","example":null},"referralStatus":{"type":"string","description":"user referral status","example":null},"referralPoints":{"type":"string","description":"user referral points","example":null},"referralResponseCode":{"type":"string","description":"referral response code","example":null},"referralResponseDesc":{"type":"string","description":"referral response description","example":null},"referralExpiration":{"type":"string","description":"referral code expiration","example":null},"earnedPoints":{"type":"string","description":"user earned reward points","example":null},"totalPoints":{"type":"string","description":"user total points","example":null},"deviceModel":{"type":"string","description":"user device type (Brand + Model)","example":null},"marketingChannel":{"type":"string","description":"marketing channel","example":null},"status":{"type":"string","description":"user account status","example":null},"role":{"type":"string","description":"user role","example":null},"level":{"type":"string","description":"user level","example":null},"response":{"type":"string","description":"response","example":null}}},"UserLevel":{"type":"object","properties":{"currentLevel":{"type":"string","description":"user current level","example":null},"statusLevelDTO":{"$ref":"#/components/schemas/StatusLevel"}}},"StatusLevel":{"type":"object","properties":{"level":{"type":"string","description":"level request level","example":null},"description":{"type":"string","description":"level request description","example":null},"status":{"type":"string","description":"level request status","example":null},"remarks":{"type":"string","description":"level request remarks","example":null},"filename":{"type":"string","description":"level request file name","example":null},"idPath":{"type":"string","description":"level request id file path","example":null},"selfieIdPath":{"type":"string","description":"level request selfie path","example":null}}},"PersonalAccount":{"type":"object","properties":{"id":{"type":"string","description":"profile ID","example":null},"created":{"type":"string","description":"date created","example":null},"version":{"type":"string","description":"date modified","example":null},"deleted":{"type":"string","description":"date deleted","example":null},"transactionAccount":{"type":"array","items":{"$ref":"#/components/schemas/TransactionAccount"}},"sourceOfFunds":{"type":"string","description":"source of fund","example":null},"fname":{"type":"string","description":"first name","example":null},"mname":{"type":"string","description":"middle name","example":null},"lname":{"type":"string","description":"last name","example":null},"birth":{"type":"string","description":"birthdate","example":null},"email":{"type":"string","description":"email address","example":null},"gender":{"type":"string","description":"gender","example":null},"phone":{"type":"string","description":"mobile phone number","example":null},"address":{"type":"string","description":"street address","example":null},"country":{"type":"string","description":"country","example":null},"province":{"type":"string","description":"province","example":null},"city":{"type":"string","description":"city","example":null},"zip":{"type":"string","description":"zip code","example":null},"jobTitle":{"type":"string","description":"job title","example":null},"userAcccount":{"$ref":"#/components/schemas/UserAccount"},"main":{"type":"boolean","description":"is main account?","example":null},"subscribed":{"type":"boolean","description":"is subscribed?","example":null},"civilStatus":{"type":"string","description":"civil status","example":null,"enum":["Single","Married","Widowed"]},"serverId":{"type":"string","description":"server ID","example":null},"accountName":{"type":"string","description":"account name","example":null}}},"TransactionAccount":{"type":"object","properties":{"id":{"type":"string","description":"transaction account ID","example":null},"created":{"type":"string","description":"date created","example":null},"version":{"type":"string","description":"date modified","example":null},"deleted":{"type":"string","description":"date deleted","example":null},"firstIdentifier":{"type":"string","description":"first identifier","example":null},"secondIdentifier":{"type":"string","description":"second identifier","example":null},"registrationId":{"type":"string","description":"registration ID","example":null},"biller":{"type":"string","description":"name of biller","example":null},"billID":{"type":"string","description":"bills payment ID","example":null},"accountName":{"type":"string","description":"account name","example":null},"sssNumber":{"type":"string","description":"sss number","example":null},"philhealthNumber":{"type":"string","description":"philhealth number","example":null},"pagibigNumber":{"type":"string","description":"pagibig number","example":null},"mp2Number":{"type":"string","description":"modified pagibig 2 number","example":null},"sssLoanNumber":{"type":"string","description":"sss loan number","example":null},"pagibigLoanNumber":{"type":"string","description":"pagibigLoanNumber","example":null},"serverId":{"type":"string","description":"server ID","example":null},"main":{"type":"boolean","description":"is main?","example":null},"tin":{"type":"string","description":"tin number","example":null},"dependent":{"type":"string","description":"number of dependents","example":null},"rdo":{"type":"string","description":"regional director's office","example":null},"payorStatus":{"type":"string","description":"payor status","example":null},"deductionScheme":{"type":"string","description":"deductionScheme","example":null},"incomes":{"type":"array","items":{"$ref":"#/components/schemas/Income"}},"expenses":{"type":"array","items":{"$ref":"#/components/schemas/Expense"}},"subscribed":{"type":"string","description":"is subscribed?","example":null},"type":{"type":"string","description":"transaction account type","example":null}}},"Income":{"type":"object","properties":{"id":{"type":"string","description":"income ID","example":null},"created":{"type":"string","description":"date created","example":null},"version":{"type":"string","description":"date modified","example":null},"deleted":{"type":"string","description":"date deleted","example":null},"amount":{"type":"string","description":"amount","example":null},"orNumber":{"type":"string","description":"or number","example":null},"paidDate":{"type":"string","description":"paid date","example":null},"category":{"type":"string","description":"category","example":null},"description":{"type":"string","description":"description","example":null},"uid":{"type":"string","description":"user account uid","example":null},"serverId":{"type":"string","description":"income server ID","example":null},"taxAccountId":{"type":"string","description":"tax account ID","example":null}}},"Expense":{"type":"object","properties":{"id":{"type":"string","description":"income ID","example":null},"created":{"type":"string","description":"date created","example":null},"version":{"type":"string","description":"date modified","example":null},"deleted":{"type":"string","description":"date deleted","example":null},"amount":{"type":"string","description":"amount","example":null},"orNumber":{"type":"string","description":"or number","example":null},"paidDate":{"type":"string","description":"paid date","example":null},"category":{"type":"string","description":"category","example":null},"description":{"type":"string","description":"description","example":null},"uid":{"type":"string","description":"user account uid","example":null},"serverId":{"type":"string","description":"income server ID","example":null},"taxAccountId":{"type":"string","description":"tax account ID","example":null}}},"GovernmentAccount":{"type":"object","properties":{"id":{"type":"string","description":"government account ID","example":null},"created":{"type":"string","description":"date created","example":null},"version":{"type":"string","description":"date modified","example":null},"deleted":{"type":"string","description":"date deleted","example":null},"accountName":{"type":"string","description":"account name","example":null},"sssNumber":{"type":"string","description":"sss number","example":null},"philhealthNumber":{"type":"string","description":"philhealth number","example":null},"pagibigNumber":{"type":"string","description":"pagibig number","example":null},"mp2Number":{"type":"string","description":"modified pagibig 2 number","example":null},"sssLoanNumber":{"type":"string","description":"sss loan number","example":null},"pagibigLoanNumber":{"type":"string","description":"pagibigLoanNumber","example":null},"serverId":{"type":"string","description":"server ID","example":null},"personal_serverId":{"type":"string","description":"personal account ID","example":null},"main":{"type":"boolean","description":"is main?","example":null}}},"Packages":{"type":"object","properties":{"id":{"type":"string","description":"package id","example":null},"name":{"type":"string","description":"package name","example":null},"price":{"type":"string","description":"package price","example":null},"services":{"type":"array","items":{"$ref":"#/components/schemas/Services"}}}},"Services":{"type":"object","properties":{"id":{"type":"string","description":"package id","example":null},"service":{"type":"string","description":"service name","example":null}}},"PartnerFees":{"type":"object","properties":{"partner":{"type":"string","description":"partner name","example":null},"fee":{"type":"number","description":"partner fee","example":null},"typeOfFee":{"type":"string","description":"partner type of fee","enum":["value","percentage"],"example":null}}},"PagIBIGRequest":{"type":"object","properties":{"govtAccountId":{"type":"number","description":"government account ID","example":null},"amountDue":{"type":"number","description":"Amount Due","example":null},"serviceCharge":{"type":"number","description":"service charge","example":null},"currency":{"type":"string","description":"currency","example":null,"enum":["PHP"]},"modeOfPayment":{"type":"string","description":"modeOfPayment","example":null,"enum":["WALLET","CTA","ECPAY","PAYPAL","7-11","DRAGON"]},"pagibigNo":{"type":"string","description":"pag-IBIG number","example":null},"paymentType":{"type":"string","description":"payment type","example":null,"enum":["Membership Savings","Modified Pag-IBIG 2","Short Term Loan","Housing Loan Amortization"]},"paymentOption":{"type":"string","description":"payment option","example":null,"enum":["Full Payment"]},"startDate":{"type":"string","description":"start date","example":null},"endDate":{"type":"string","description":"end date","example":null},"totalPaymentDue":{"type":"number","description":"total payment due","example":null},"payorType":{"type":"string","description":"payor type","example":null,"enum":["OFW","Voluntary","Individual","Self-Employed","Employer"]},"backEndFee":{"type":"number","description":"backend fee","example":null},"pagibigLoanNumber":{"type":"string","description":"pagibigLoanNumber","example":null},"pin":{"type":"string","description":"PIN","example":null},"branchCode":{"type":"string","description":"branch code","example":null},"sourceCountry":{"type":"string","description":"source country","example":null},"memberName":{"type":"string","description":"member name","example":null},"promoCode":{"type":"string","description":"promo code","example":null},"discount":{"type":"number","description":"discount","example":null}}},"PagIBIGResponse":{"type":"object","properties":{"transactionId":{"type":"string","description":"transaction ID","example":null},"govtAccountId":{"type":"number","description":"government account ID","example":null},"amountDue":{"type":"number","description":"Amount Due","example":null},"serviceCharge":{"type":"number","description":"service charge","example":null},"confirmationCode":{"type":"string","description":"confirmation code","example":null},"currency":{"type":"string","description":"currency","example":null,"enum":["PHP"]},"modeOfPayment":{"type":"string","description":"modeOfPayment","example":null,"enum":["WALLET","CTA","ECPAY","PAYPAL","7-11","DRAGON"]},"pagibigNo":{"type":"string","description":"pag-IBIG number","example":null},"paymentType":{"type":"string","description":"payment type","example":null,"enum":["Membership Savings","Modified Pag-IBIG 2","Short Term Loan","Housing Loan Amortization"]},"paymentOption":{"type":"string","description":"payment option","example":null,"enum":["Full Payment"]},"startDate":{"type":"string","description":"start date","example":null},"endDate":{"type":"string","description":"end date","example":null},"token":{"type":"string","description":"token for dragon pay","example":null},"totalPaymentDue":{"type":"number","description":"total payment due","example":null},"payorType":{"type":"string","description":"payor type","example":null,"enum":["OFW","Voluntary","Individual","Self-Employed","Employer"]},"created":{"type":"string","description":"date created","example":null},"canAcceptPayment":{"type":"boolean","description":"is can accept payment","example":null},"errorMessage":{"type":"string","description":"error message if canAcceptPayment is false","example":null},"serverId":{"type":"string","description":"server ID","example":null},"status":{"type":"string","description":"status","example":null,"enum":["POSTED","PROCESSING","PAID","VOIDED","AWAITING_PAYMENT","ENCODED"]},"response":{"type":"string","description":"response","example":null},"backEndFee":{"type":"number","description":"backend fee","example":null},"pagibigLoanNumber":{"type":"string","description":"pagibigLoanNumber","example":null},"pin":{"type":"string","description":"PIN","example":null},"branchCode":{"type":"string","description":"branch code","example":null},"sourceCountry":{"type":"string","description":"source country","example":null},"memberName":{"type":"string","description":"member name","example":null},"items":{"type":"array","items":{"$ref":"#/components/schemas/Item"}},"promoCode":{"type":"string","description":"promo code","example":null},"discount":{"type":"number","description":"discount","example":null}}},"PagIBIGEmployerInfo":{"type":"object","properties":{"canAcceptPayment":{"type":"boolean","description":"is can accept payment","example":null},"pin":{"type":"string","description":"PIN","example":null},"branchCode":{"type":"string","description":"branch code","example":null},"employerName":{"type":"string","description":"employer name","example":null},"transactionId":{"type":"string","description":"transaction ID","example":null},"amountDue":{"type":"string","description":"amount due","example":null},"errorMessage":{"type":"string","description":"error message if canAcceptPayment is false","enum":["(contains) expired","(contains) cancelled","(contains) posted","(contains) receved by collecting partner.","(contains) received by Pag-IBIG Fund."],"example":null},"items":{"type":"array","items":{"$ref":"#/components/schemas/Item"}}}},"Item":{"type":"object","properties":{"programCode":{"type":"string","description":"program code","example":null},"startDate":{"type":"string","description":"start date","example":null},"endDate":{"type":"string","description":"end date","example":null},"employeeAmount":{"type":"string","description":"employee amount","example":null},"employerAmount":{"type":"string","description":"employer amount","example":null},"count":{"type":"string","description":"count","example":null}}},"PhilHealthRequest":{"type":"object","properties":{"govtAccountId":{"type":"number","description":"government account ID","example":null},"amountDue":{"type":"number","description":"Amount Due","example":null},"serviceCharge":{"type":"number","description":"service charge","example":"="},"currency":{"type":"string","description":"currency","example":null,"enum":["PHP"]},"modeOfPayment":{"type":"string","description":"modeOfPayment","example":null,"enum":["WALLET","CTA","ECPAY","PAYPAL","7-11","DRAGON"]},"philhealthId":{"type":"string","description":"PhilHealth number","example":null},"payorType":{"type":"string","description":"payor type","example":null,"enum":["OFW","Voluntary","Self-Employed","Employer"]},"startDate":{"type":"string","description":"start date","example":null},"endDate":{"type":"string","description":"end date","example":null},"totalPaymentDue":{"type":"number","description":"total payment due","example":null},"backEndFee":{"type":"number","description":"backend fee","example":null},"salary":{"type":"string","description":"salary","example":null},"term":{"type":"string","description":"term","example":null},"memberName":{"type":"string","description":"member name","example":null},"pin":{"type":"string","description":"PIN","example":null},"promoCode":{"type":"string","description":"promo code","example":null},"discount":{"type":"number","description":"discount","example":null}}},"PhilHealthResponse":{"type":"object","properties":{"transactionId":{"type":"string","description":"transaction ID","example":null},"govtAccountId":{"type":"number","description":"government account ID","example":null},"amountDue":{"type":"number","description":"Amount Due","example":null},"serviceCharge":{"type":"number","description":"service charge","example":null},"confirmationCode":{"type":"string","description":"confirmation code","example":null},"currency":{"type":"string","description":"currency","example":null,"enum":["PHP"]},"modeOfPayment":{"type":"string","description":"modeOfPayment","example":null,"enum":["WALLET","CTA","ECPAY","PAYPAL","7-11","DRAGON"]},"philhealthId":{"type":"string","description":"PhilHealth number","example":null},"payorType":{"type":"string","description":"payor type","example":null,"enum":["OFW","Voluntary","Self-Employed","Employer"]},"startDate":{"type":"string","description":"start date","example":null},"endDate":{"type":"string","description":"end date","example":null},"created":{"type":"string","description":"date created","example":null},"status":{"type":"string","description":"status","example":null,"enum":["POSTED","PROCESSING","PAID","VOIDED","AWAITING_PAYMENT","ENCODED"]},"response":{"type":"string","description":"response","example":null},"serverId":{"type":"string","description":"server ID","example":null},"token":{"type":"string","description":"token for dragon pay","example":null},"totalPaymentDue":{"type":"number","description":"total payment due","example":null},"backEndFee":{"type":"number","description":"backend fee","example":null},"salary":{"type":"string","description":"salary","example":null},"term":{"type":"string","description":"term","example":null},"memberName":{"type":"string","description":"member name","example":null},"pin":{"type":"string","description":"PIN","example":null},"promoCode":{"type":"string","description":"promo code","example":null},"discount":{"type":"number","description":"discount","example":null}}},"MemberBean":{"type":"object","properties":{"eename":{"type":"string","description":"ee name","example":null},"eenum":{"type":"string","description":"ee num","example":null},"errorMessage":{"type":"string","description":"error message","example":null},"fapld":{"type":"string","description":"fapld","example":null},"iprnum":{"type":"string","description":"ipr num","example":null},"pdfPath":{"type":"string","description":"pdf path","example":null},"repcd":{"type":"string","description":"repcd","example":null},"repdt":{"type":"string","description":"repdt","example":null},"tapld":{"type":"string","description":"tapld","example":null},"tsamt":{"type":"string","description":"tsamt","example":null}}},"EmployerBean":{"type":"object","properties":{"amount":{"type":"string","description":"amount","example":null},"appmo":{"type":"string","description":"app mo","example":null},"brnum":{"type":"string","description":"br num","example":null},"erbrn":{"type":"string","description":"er brn","example":null},"ername":{"type":"string","description":"er name","example":null},"ernum":{"type":"string","description":"er num","example":null},"replyCode":{"type":"string","description":"reply code","example":null},"replyDate":{"type":"string","description":"reply date","example":null}}},"SSSContributionRequest":{"type":"object","properties":{"govtAccountId":{"type":"number","description":"government account ID","example":null},"amountDue":{"type":"number","description":"Amount Due","example":null},"contriAmount":{"type":"number","description":"contribution amount","example":null},"serviceCharge":{"type":"number","description":"service charge","example":null},"currency":{"type":"string","description":"currency","example":null,"enum":["PHP"]},"modeOfPayment":{"type":"string","description":"modeOfPayment","example":null,"enum":["WALLET","CTA","ECPAY","PAYPAL","7-11","DRAGON"]},"sssNumber":{"type":"string","description":"sss number","example":null},"prnNumber":{"type":"string","description":"sss number","example":null},"sssType":{"type":"string","description":"sssType","example":null,"enum":["Contribution","Real Estate Loan","Salary Loan"]},"startDate":{"type":"string","description":"start date","example":null},"endDate":{"type":"string","description":"end date","example":null},"totalPaymentDue":{"type":"number","description":"total payment due","example":null},"backEndFee":{"type":"number","description":"backend fee","example":null},"flexiFund":{"type":"number","description":"sss flexi fund","example":null},"payorType":{"type":"string","description":"payor type","example":null,"enum":["Self-Employed","Voluntary","Non Working Spouse","OFW","Individual","Employer"]},"term":{"type":"string","description":"term","example":null},"sourceCountry":{"type":"string","description":"source country","example":null},"memberName":{"type":"string","description":"member name","example":null},"promoCode":{"type":"string","description":"promo code","example":null},"discount":{"type":"number","description":"discount","example":null}}},"SSSSalaryLoanRequest":{"type":"object","properties":{"govtAccountId":{"type":"number","description":"government account ID","example":null},"amountDue":{"type":"number","description":"Amount Due","example":null},"serviceCharge":{"type":"number","description":"service charge","example":null},"currency":{"type":"string","description":"currency","example":null,"enum":["PHP"]},"modeOfPayment":{"type":"string","description":"modeOfPayment","example":null,"enum":["WALLET","CTA","ECPAY","PAYPAL","7-11","DRAGON"]},"sssNumber":{"type":"string","description":"sss number","example":null},"sssType":{"type":"string","description":"sssType","example":null,"enum":["Contribution","Real Estate Loan","Salary Loan"]},"totalPaymentDue":{"type":"number","description":"total payment due","example":null},"backEndFee":{"type":"number","description":"backend fee","example":null},"applicableMonth":{"type":"string","description":"salary loan applicable month","example":null},"payorType":{"type":"string","description":"payor type","example":null,"enum":["Self-Employed","Voluntary","Non Working Spouse","OFW","Individual","Employer"]},"memberName":{"type":"string","description":"member name","example":null},"promoCode":{"type":"string","description":"promo code","example":null},"discount":{"type":"number","description":"discount","example":null}}},"SSSRealEstateRequest":{"type":"object","properties":{"govtAccountId":{"type":"number","description":"government account ID","example":null},"amountDue":{"type":"number","description":"Amount Due","example":null},"serviceCharge":{"type":"number","description":"service charge","example":null},"currency":{"type":"string","description":"currency","example":null,"enum":["PHP"]},"modeOfPayment":{"type":"string","description":"modeOfPayment","example":null,"enum":["WALLET","CTA","ECPAY","PAYPAL","7-11","DRAGON"]},"sssNumber":{"type":"string","description":"sss number","example":null},"sssType":{"type":"string","description":"sssType","example":null,"enum":["Contribution","Real Estate Loan","Salary Loan"]},"totalPaymentDue":{"type":"number","description":"total payment due","example":null},"backEndFee":{"type":"number","description":"backend fee","example":null},"payorType":{"type":"string","description":"payor type","example":null,"enum":["Self-Employed","Voluntary","Non Working Spouse","OFW","Individual","Employer"]},"loanAccountNumber":{"type":"string","description":"sss real estate loan account number","example":null},"memberName":{"type":"string","description":"member name","example":null},"promoCode":{"type":"string","description":"promo code","example":null},"discount":{"type":"number","description":"discount","example":null}}},"SSSResponse":{"type":"object","properties":{"prnNumber":{"type":"string","description":"sss prn","example":null},"prnStatus":{"type":"string","description":"sss prn status","example":null},"transactionId":{"type":"string","description":"transaction ID","example":null},"govtAccountId":{"type":"number","description":"government account ID","example":null},"amountDue":{"type":"number","description":"Amount Due","example":null},"contriAmount":{"type":"number","description":"contribution amount","example":null},"serviceCharge":{"type":"number","description":"service charge","example":null},"confirmationCode":{"type":"string","description":"confirmation code","example":null},"currency":{"type":"string","description":"currency","example":null,"enum":["PHP"]},"modeOfPayment":{"type":"string","description":"modeOfPayment","example":null,"enum":["WALLET","CTA","ECPAY","PAYPAL","7-11","DRAGON"]},"sssNumber":{"type":"string","description":"sss number","example":null},"sssType":{"type":"string","description":"sssType","example":null,"enum":["Contribution","Real Estate Loan","Salary Loan"]},"startDate":{"type":"string","description":"start date","example":null},"endDate":{"type":"string","description":"end date","example":null},"totalPaymentDue":{"type":"number","description":"total payment due","example":null},"backEndFee":{"type":"number","description":"backend fee","example":null},"flexiFund":{"type":"number","description":"sss flexi fund","example":null},"applicableMonth":{"type":"string","description":"salary loan applicable month","example":null},"payorType":{"type":"string","description":"payor type","example":null,"enum":["Self-Employed","Voluntary","Non Working Spouse","OFW","Individual","Employer"]},"loanAccountNumber":{"type":"string","description":"sss real estate loan account number","example":null},"serverId":{"type":"string","description":"server ID","example":null},"status":{"type":"string","description":"status","example":null,"enum":["POSTED","PROCESSING","PAID","VOIDED","AWAITING_PAYMENT","ENCODED"]},"response":{"type":"string","description":"response","example":null},"term":{"type":"string","description":"term","example":null},"created":{"type":"string","description":"date created","example":null},"sourceCountry":{"type":"string","description":"source country","example":null},"memberName":{"type":"string","description":"member name","example":null},"promoCode":{"type":"string","description":"promo code","example":null},"discount":{"type":"number","description":"discount","example":null}}},"AccessTokenJwt":{"type":"object","properties":{"accessToken":{"type":"string","description":"access token","example":null},"refreshToken":{"type":"string","description":"refresh token","example":null},"role":{"type":"string","description":"refresh token","example":null},"userId":{"type":"string","description":"refresh token","example":null}}},"Notification":{"type":"object","properties":{"id":{"type":"string","description":"id","example":null},"created":{"type":"string","description":"created","example":null},"version":{"type":"string","description":"version","example":null},"deleted":{"type":"string","description":"deleted","example":null},"title":{"type":"string","description":"title","example":null},"message":{"type":"string","description":"message","example":null},"description":{"type":"string","description":"description","example":null},"createdTimeStamp":{"type":"string","description":"created timestamp","example":null},"deletedTimeStamp":{"type":"string","description":"deleted timestamp","example":null}}}}}}