{"openapi":"3.0.0","servers":[{"url":"https://virtserver.swaggerhub.com/shivek/tickets-rgm-buslane-demo/1.0.0","description":"Tikets Api for Ramat Gan Municipal BusLane Demo"}],"info":{"description":"Tikets Api for Ramat Gan Municipal BusLane Demo","version":"1.0.0","title":"Tickets Api","contact":{"email":"yair@shivek.co.il"},"license":{"name":"Apache 2.0","url":"http://www.apache.org/licenses/LICENSE-2.0.html"}},"tags":[{"name":"admins","description":"Secured Admin-only calls"},{"name":"Operations","description":"Operations available for calls comming from the workflow API Managment or authenticated testers"}],"paths":{"/generateTicket":{"post":{"tags":["Operations"],"summary":"Generate BusLane Transportation Violation Ticket","operationId":"generateTicket","description":"this operation will receive the Vehicle Owner Contact Information will produse a ticket and push it to delivery.","responses":{"200":{"description":"Successful ticket generation.","content":{"application/json":{"schema":{"type":"object","properties":{"ticketNumber":{"description":"A uniqe ticket identifier","type":"string","format":"uuid","example":"732ab34f-4414-4b94-abaf-ed2b37c01a4e"}}}}}},"400":{"description":"can not generate ticket for the given info "},"409":{"description":"Ticket alreday had been generated for this issue"}},"requestBody":{"content":{"application/json":{"schema":{"type":"object","properties":{"cameraTake":{"$ref":"#/components/schemas/cameraTake"},"CarOwnerAddres":{"$ref":"#/components/schemas/CarOwnerAddres"}}}}}}}}},"components":{"schemas":{"cameraTake":{"type":"object","required":["cameraId","time","photos"],"properties":{"cameraId":{"description":"Camera Uniqe Identifier","type":"string","format":"uuid","example":"123e4567-e89b-12d3-a456-426655440000"},"time":{"description":"Time of camera shooting","type":"string","format":"date-time","example":"2020-04-16T17:32:28Z"},"photos":{"description":"Car photos to be investigated","type":"array","items":{"type":"string","format":"byte"}}}},"CarOwnerAddres":{"type":"object","required":["id","vehicleRegId","name","address"],"properties":{"id":{"type":"string","example":5.8015521E7},"vehicleRegId":{"type":"string","example":"830-40-301"},"name":{"$ref":"#/components/schemas/fullName"},"address":{"$ref":"#/components/schemas/address"}}},"fullName":{"type":"object","required":["firstName","lastName"],"properties":{"firstName":{"type":"string","example":"Yosef"},"lastName":{"type":"string","example":"Cohen"},"middleInitials":{"type":"string","example":"Jr."}}},"address":{"type":"object","required":["street","city","zipCode"],"properties":{"street":{"type":"string","example":"123 Herzel Street"},"city":{"type":"string","example":"Haifa"},"zipCode":{"type":"string","example":33670}}}}}}